LICENSE-APACHE
LICENSE-MIT
Pipfile
Pipfile.lock
README.md
publish.cmd
setup.py
stack.chat.egg-info/PKG-INFO
stack.chat.egg-info/SOURCES.txt
stack.chat.egg-info/dependency_links.txt
stack.chat.egg-info/entry_points.txt
stack.chat.egg-info/requires.txt
stack.chat.egg-info/top_level.txt
stackchat/__init__.py
stackchat/__main__.py
stackchat/_version.py
stackchat/_util/__init__.py
stackchat/_util/async.py
stackchat/_util/emncojiding.py
stackchat/_util/emncojiding_test.py
stackchat/_util/names.py
stackchat/_util/obj_dict.py
stackchat/cli/__init__.py
stackchat/cli/config/__init__.py
stackchat/cli/init/__init__.py
stackchat/cli/most_replied/__init__.py
stackchat/cli/send/__init__.py
stackchat/cli/tail/__init__.py
stackchat/cli/web/__init__.py
stackchat/client/__init__.py
stackchat/client/sources.py
stackchat/client/_request/__init__.py
stackchat/data/__init__.py
stackchat/data/_constants.py
stackchat/data/_seed.py
stackchat/data/models.py
stackchat/parse/__init__.py
stackchat/parse/_base.py
stackchat/parse/html/__init__.py
stackchat/parse/html/_base.py
stackchat/parse/html/fkey.py
stackchat/parse/html/home.py
stackchat/parse/html/navbar.py
stackchat/parse/html/transcript_day.py
stackchat/parse/html/transcript_day_test.py
stackchat/parse/json/__init__.py
stackchat/parse/json/_base.py
stackchat/parse/json/events.py
stackchat/parse/json/events_test.py