Metadata-Version: 1.2
Name: stack.chat
Version: 3.1.0.dev1513065255
Summary: an unofficial Python 3 library and command-line tool for [Stack Exchange chat](https://chat.stackexchange.com/faq)
Home-page: https://stack.chat
Author: Jeremy Banks
Author-email: _@jeremy.ca
License: MIT
Platform: UNKNOWN
Classifier: Programming Language :: Python :: 3
Classifier: License :: OSI Approved :: Apache Software License
Classifier: License :: OSI Approved :: MIT License
Requires-Python: >=3
